uraster/__init__.py
uraster/utility.py
uraster/classes/__init__.py
uraster/classes/_visual.py
uraster/classes/sraster.py
uraster/classes/uraster.py
uraster/mesh/__init__.py
uraster/mesh/dggs.py
uraster/mesh/mpas.py
uraster/operation/__init__.py
uraster/operation/extract.py
uraster/operation/intersect.py
uraster-0.1.6.dist-info/LICENSE
uraster-0.1.6.dist-info/METADATA
uraster-0.1.6.dist-info/WHEEL
uraster-0.1.6.dist-info/top_level.txt
uraster-0.1.6.dist-info/RECORD
