Metadata-Version: 2.1
Name: uraster
Version: 0.1.6
Summary: A Python package for unstructured raster processing and remapping
Author-email: Chang Liao <changliao.climate@gmail.com>
Maintainer-email: Chang Liao <changliao.climate@gmail.com>
License: BSD 3-Clause License
Project-URL: Homepage, https://github.com/changliao1025/uraster
Project-URL: Documentation, https://github.com/changliao1025/uraster
Project-URL: Repository, https://github.com/changliao1025/uraster
Project-URL: Bug Tracker, https://github.com/changliao1025/uraster/issues
Keywords: raster,GIS,geospatial,GDAL,unstructured
Classifier: Development Status :: 3 - Alpha
Classifier: Intended Audience :: Science/Research
Classifier: License :: OSI Approved :: BSD License
Classifier: Operating System :: OS Independent
Classifier: Programming Language :: Python :: 3
Classifier: Programming Language :: Python :: 3.8
Classifier: Programming Language :: Python :: 3.9
Classifier: Programming Language :: Python :: 3.10
Classifier: Programming Language :: Python :: 3.11
Classifier: Topic :: Scientific/Engineering :: GIS
Requires-Python: >=3.8
License-File: LICENSE
Requires-Dist: numpy>=1.19.0
Requires-Dist: gdal>=3.0.0
Requires-Dist: pyearth>=0.1.29
Requires-Dist: psutil>=5.0.0
Requires-Dist: pooch>=1.6.0
Requires-Dist: tqdm>=4.0.0
Requires-Dist: trame>=2.0.0
Requires-Dist: trame-vtk>=2.0.0
Requires-Dist: trame-vuetify>=2.0.0
Requires-Dist: ipywidgets>=7.0.0
Requires-Dist: geovista>=0.3.0
Requires-Dist: vtk==9.3.0
Provides-Extra: dev
Requires-Dist: pytest>=6.0; extra == "dev"
Requires-Dist: pytest-cov; extra == "dev"
Requires-Dist: black; extra == "dev"
Requires-Dist: flake8; extra == "dev"
Requires-Dist: mypy; extra == "dev"
Provides-Extra: docs
Requires-Dist: sphinx; extra == "docs"
Requires-Dist: sphinx-rtd-theme; extra == "docs"
